{
  "en": [
    {
      "id": "maken-no-daydreamer-1",
      "number": "1",
      "title": "",
      "date": "2019/01/23",
      "pages": []
    },
    {
      "id": "maken-no-daydreamer-2",
      "number": "2",
      "title": "",
      "date": "2019/01/23",
      "pages": []
    },
    {
      "id": "maken-no-daydreamer-3",
      "number": "3",
      "title": "",
      "date": "2019/01/23",
      "pages": []
    },
    {
      "id": "maken-no-daydreamer-4",
      "number": "4",
      "title": "",
      "date": "2019/01/23",
      "pages": []
    },
    {
      "id": "maken-no-daydreamer-5",
      "number": "5",
      "title": "",
      "date": "2019/01/23",
      "pages": []
    },
    {
      "id": "maken-no-daydreamer-6",
      "number": "6",
      "title": "",
      "date": "2019/01/23",
      "pages": []
    },
    {
      "id": "maken-no-daydreamer-7",
      "number": "7",
      "title": "",
      "date": "2019/01/23",
      "pages": []
    },
    {
      "id": "maken-no-daydreamer-8",
      "number": "8",
      "title": "",
      "date": "2019/01/23",
      "pages": []
    },
    {
      "id": "maken-no-daydreamer-9",
      "number": "9",
      "title": "",
      "date": "2019/01/23",
      "pages": []
    },
    {
      "id": "maken-no-daydreamer-10",
      "number": "10",
      "title": "",
      "date": "2019/01/23",
      "pages": []
    },
    {
      "id": "maken-no-daydreamer-11",
      "number": "11",
      "title": "",
      "date": "2019/01/23",
      "pages": []
    },
    {
      "id": "maken-no-daydreamer-12",
      "number": "12",
      "title": "",
      "date": "2019/01/23",
      "pages": []
    },
    {
      "id": "maken-no-daydreamer-13",
      "number": "13",
      "title": "",
      "date": "2019/01/23",
      "pages": []
    },
    {
      "id": "maken-no-daydreamer-14",
      "number": "14",
      "title": "",
      "date": "2019/01/23",
      "pages": []
    },
    {
      "id": "maken-no-daydreamer-15",
      "number": "15",
      "title": "",
      "date": "2019/01/23",
      "pages": []
    },
    {
      "id": "maken-no-daydreamer-16",
      "number": "16",
      "title": "",
      "date": "2019/01/23",
      "pages": []
    },
    {
      "id": "maken-no-daydreamer-17",
      "number": "17",
      "title": "",
      "date": "2019/01/23",
      "pages": []
    },
    {
      "id": "maken-no-daydreamer-18",
      "number": "18",
      "title": "",
      "date": "2019/01/23",
      "pages": []
    },
    {
      "id": "maken-no-daydreamer-19",
      "number": "19",
      "title": "",
      "date": "2019/01/23",
      "pages": []
    },
    {
      "id": "maken-no-daydreamer-20",
      "number": "20",
      "title": "",
      "date": "2019/01/23",
      "pages": []
    },
    {
      "id": "maken-no-daydreamer-21",
      "number": "21",
      "title": "",
      "date": "2019/01/23",
      "pages": []
    },
    {
      "id": "maken-no-daydreamer-22",
      "number": "22",
      "title": "",
      "date": "2019/01/23",
      "pages": []
    },
    {
      "id": "maken-no-daydreamer-23",
      "number": "23",
      "title": "",
      "date": "2019/01/23",
      "pages": []
    },
    {
      "id": "maken-no-daydreamer-24",
      "number": "24",
      "title": "",
      "date": "2019/01/23",
      "pages": []
    },
    {
      "id": "maken-no-daydreamer-25",
      "number": "25",
      "title": "",
      "date": "2019/01/23",
      "pages": []
    },
    {
      "id": "maken-no-daydreamer-26",
      "number": "26",
      "title": "",
      "date": "2019/01/23",
      "pages": []
    },
    {
      "id": "maken-no-daydreamer-27",
      "number": "27",
      "title": "",
      "date": "2019/01/23",
      "pages": []
    },
    {
      "id": "maken-no-daydreamer-28",
      "number": "28",
      "title": "",
      "date": "2019/01/23",
      "pages": []
    },
    {
      "id": "maken-no-daydreamer-29",
      "number": "29",
      "title": "",
      "date": "2019/01/23",
      "pages": []
    },
    {
      "id": "maken-no-daydreamer-30",
      "number": "30",
      "title": "",
      "date": "2019/02/26",
      "pages": []
    },
    {
      "id": "maken-no-daydreamer-31",
      "number": "31",
      "title": "",
      "date": "2019/03/07",
      "pages": []
    },
    {
      "id": "maken-no-daydreamer-32",
      "number": "32",
      "title": "",
      "date": "2019/08/25",
      "pages": []
    },
    {
      "id": "maken-no-daydreamer-33",
      "number": "33",
      "title": "",
      "date": "2019/08/25",
      "pages": []
    },
    {
      "id": "maken-no-daydreamer-34",
      "number": "34",
      "title": "",
      "date": "2019/08/25",
      "pages": []
    },
    {
      "id": "maken-no-daydreamer-35",
      "number": "35",
      "title": "",
      "date": "2019/08/25",
      "pages": []
    },
    {
      "id": "maken-no-daydreamer-36",
      "number": "36",
      "title": "",
      "date": "2019/08/25",
      "pages": []
    },
    {
      "id": "maken-no-daydreamer-37",
      "number": "37",
      "title": "",
      "date": "2019/11/06",
      "pages": []
    },
    {
      "id": "maken-no-daydreamer-38",
      "number": "38",
      "title": "",
      "date": "2019/11/06",
      "pages": []
    },
    {
      "id": "maken-no-daydreamer-39",
      "number": "39",
      "title": "",
      "date": "2019/11/19",
      "pages": []
    },
    {
      "id": "maken-no-daydreamer-40",
      "number": "40",
      "title": "",
      "date": "2020/07/08",
      "pages": []
    },
    {
      "id": "maken-no-daydreamer-41",
      "number": "41",
      "title": "",
      "date": "2020/07/10",
      "pages": []
    },
    {
      "id": "maken-no-daydreamer-42",
      "number": "42",
      "title": "",
      "date": "2020/07/19",
      "pages": []
    },
    {
      "id": "maken-no-daydreamer-43",
      "number": "43",
      "title": "",
      "date": "2020/07/22",
      "pages": []
    },
    {
      "id": "maken-no-daydreamer-44",
      "number": "44",
      "title": "",
      "date": "2020/12/10",
      "pages": []
    },
    {
      "id": "maken-no-daydreamer-45",
      "number": "45",
      "title": "",
      "date": "2021/02/09",
      "pages": []
    },
    {
      "id": "maken-no-daydreamer-46",
      "number": "46",
      "title": "",
      "date": "2021/05/11",
      "pages": []
    },
    {
      "id": "maken-no-daydreamer-47",
      "number": "47",
      "title": "",
      "date": "2021/10/26",
      "pages": []
    },
    {
      "id": "maken-no-daydreamer-48",
      "number": "48",
      "title": "",
      "date": "2023/12/06",
      "pages": []
    },
    {
      "id": "maken-no-daydreamer-49",
      "number": "49",
      "title": "",
      "date": "2023/12/06",
      "pages": []
    },
    {
      "id": "maken-no-daydreamer-50",
      "number": "50",
      "title": "",
      "date": "2023/12/06",
      "pages": []
    },
    {
      "id": "maken-no-daydreamer-51",
      "number": "51",
      "title": "",
      "date": "2023/12/06",
      "pages": []
    },
    {
      "id": "maken-no-daydreamer-52",
      "number": "52",
      "title": "",
      "date": "2023/12/06",
      "pages": []
    },
    {
      "id": "maken-no-daydreamer-53",
      "number": "53",
      "title": "",
      "date": "2023/12/08",
      "pages": []
    },
    {
      "id": "maken-no-daydreamer-54",
      "number": "54",
      "title": "",
      "date": "2023/12/08",
      "pages": []
    },
    {
      "id": "maken-no-daydreamer-55",
      "number": "55",
      "title": "",
      "date": "2023/12/08",
      "pages": []
    },
    {
      "id": "maken-no-daydreamer-56",
      "number": "56",
      "title": "",
      "date": "2023/12/08",
      "pages": []
    },
    {
      "id": "maken-no-daydreamer-57",
      "number": "57",
      "title": "",
      "date": "2023/12/08",
      "pages": []
    },
    {
      "id": "maken-no-daydreamer-58",
      "number": "58",
      "title": "",
      "date": "2023/12/22",
      "pages": []
    },
    {
      "id": "maken-no-daydreamer-59",
      "number": "59",
      "title": "",
      "date": "2023/12/22",
      "pages": []
    },
    {
      "id": "maken-no-daydreamer-60",
      "number": "60",
      "title": "",
      "date": "2024/01/04",
      "pages": []
    },
    {
      "id": "maken-no-daydreamer-61",
      "number": "61",
      "title": "",
      "date": "2024/01/07",
      "pages": []
    }
  ]
}