{
  "en": [
    {
      "id": "mangadistrict-sumire-16-sai-ch-1",
      "number": "1",
      "title": "Chapter 1 - Encounter",
      "date": "2026-07-02",
      "pages": [],
      "src": "mangadistrict",
      "chapterUrl": "https://mangadistrict.com/series/sumire-16-sai/chapter-1-encounter/"
    },
    {
      "id": "mangadistrict-sumire-16-sai-ch-2",
      "number": "2",
      "title": "Chapter 2 - Smile",
      "date": "2026-07-02",
      "pages": [],
      "src": "mangadistrict",
      "chapterUrl": "https://mangadistrict.com/series/sumire-16-sai/chapter-2-smile/"
    },
    {
      "id": "mangadistrict-sumire-16-sai-ch-3",
      "number": "3",
      "title": "Chapter 3 - The Prodigial Daughter",
      "date": "2026-07-02",
      "pages": [],
      "src": "mangadistrict",
      "chapterUrl": "https://mangadistrict.com/series/sumire-16-sai/chapter-3-the-prodigial-daughter/"
    },
    {
      "id": "mangadistrict-sumire-16-sai-ch-4",
      "number": "4",
      "title": "Chapter 4 - Let's Join a Club -Part 1-",
      "date": "2026-07-02",
      "pages": [],
      "src": "mangadistrict",
      "chapterUrl": "https://mangadistrict.com/series/sumire-16-sai/chapter-4-lets-join-a-club-part-1/"
    },
    {
      "id": "mangadistrict-sumire-16-sai-ch-5",
      "number": "5",
      "title": "Chapter 5 - Let's Join a Club -Part 2-",
      "date": "2026-07-02",
      "pages": [],
      "src": "mangadistrict",
      "chapterUrl": "https://mangadistrict.com/series/sumire-16-sai/chapter-5-lets-join-a-club-part-2/"
    },
    {
      "id": "mangadistrict-sumire-16-sai-ch-6",
      "number": "6",
      "title": "Chapter 6 - Outside of Calculations",
      "date": "2026-07-02",
      "pages": [],
      "src": "mangadistrict",
      "chapterUrl": "https://mangadistrict.com/series/sumire-16-sai/chapter-6-outside-of-calculations/"
    },
    {
      "id": "mangadistrict-sumire-16-sai-ch-7",
      "number": "7",
      "title": "Chapter 7 - Swim!! Susuki-kun",
      "date": "2026-07-02",
      "pages": [],
      "src": "mangadistrict",
      "chapterUrl": "https://mangadistrict.com/series/sumire-16-sai/chapter-7-swim-susuki-kun/"
    },
    {
      "id": "mangadistrict-sumire-16-sai-ch-8",
      "number": "8",
      "title": "Chapter 8 - The Blue-eyed Samurai",
      "date": "2026-07-02",
      "pages": [],
      "src": "mangadistrict",
      "chapterUrl": "https://mangadistrict.com/series/sumire-16-sai/chapter-8-the-blue-eyed-samurai/"
    },
    {
      "id": "mangadistrict-sumire-16-sai-ch-9",
      "number": "9",
      "title": "Chapter 9 - Lex in Love",
      "date": "2026-07-02",
      "pages": [],
      "src": "mangadistrict",
      "chapterUrl": "https://mangadistrict.com/series/sumire-16-sai/chapter-9-lex-in-love/"
    },
    {
      "id": "mangadistrict-sumire-16-sai-ch-10",
      "number": "10",
      "title": "Chapter 10 - Miss Shot",
      "date": "2026-07-02",
      "pages": [],
      "src": "mangadistrict",
      "chapterUrl": "https://mangadistrict.com/series/sumire-16-sai/chapter-10-miss-shot/"
    },
    {
      "id": "mangadistrict-sumire-16-sai-ch-11",
      "number": "11",
      "title": "Chapter 11 - Sumire Will Teach You a Way to Talk Casually With Girls",
      "date": "2026-07-02",
      "pages": [],
      "src": "mangadistrict",
      "chapterUrl": "https://mangadistrict.com/series/sumire-16-sai/chapter-11-sumire-will-teach-you-a-way-to-talk-casually-with-girls/"
    },
    {
      "id": "mangadistrict-sumire-16-sai-ch-12",
      "number": "12",
      "title": "Chapter 12 - Problem",
      "date": "2026-07-02",
      "pages": [],
      "src": "mangadistrict",
      "chapterUrl": "https://mangadistrict.com/series/sumire-16-sai/chapter-12-problem/"
    },
    {
      "id": "mangadistrict-sumire-16-sai-ch-13",
      "number": "13",
      "title": "Chapter 13 - Big Trouble! The Summer Fireworks Festival",
      "date": "2026-07-02",
      "pages": [],
      "src": "mangadistrict",
      "chapterUrl": "https://mangadistrict.com/series/sumire-16-sai/chapter-13-big-trouble-the-summer-fireworks-festival/"
    },
    {
      "id": "mangadistrict-sumire-16-sai-ch-14",
      "number": "14",
      "title": "Chapter 14 - Cupid of Love",
      "date": "2026-07-02",
      "pages": [],
      "src": "mangadistrict",
      "chapterUrl": "https://mangadistrict.com/series/sumire-16-sai/chapter-14-cupid-of-love/"
    },
    {
      "id": "mangadistrict-sumire-16-sai-ch-15",
      "number": "15",
      "title": "Chapter 15 - Decide it!! The Goal of Friendship",
      "date": "2026-07-02",
      "pages": [],
      "src": "mangadistrict",
      "chapterUrl": "https://mangadistrict.com/series/sumire-16-sai/chapter-15-decide-it-the-goal-of-friendship/"
    },
    {
      "id": "mangadistrict-sumire-16-sai-ch-16",
      "number": "16",
      "title": "Chapter 16 - Happy School",
      "date": "2026-07-02",
      "pages": [],
      "src": "mangadistrict",
      "chapterUrl": "https://mangadistrict.com/series/sumire-16-sai/chapter-16-happy-school/"
    },
    {
      "id": "mangadistrict-sumire-16-sai-ch-17",
      "number": "17",
      "title": "Chapter 17 - Fear! The Sleepover Study Group!!",
      "date": "2026-07-02",
      "pages": [],
      "src": "mangadistrict",
      "chapterUrl": "https://mangadistrict.com/series/sumire-16-sai/chapter-17-fear-the-sleepover-study-group/"
    },
    {
      "id": "mangadistrict-sumire-16-sai-ch-18",
      "number": "18",
      "title": "Chapter 18 - Demon Teacher",
      "date": "2026-07-02",
      "pages": [],
      "src": "mangadistrict",
      "chapterUrl": "https://mangadistrict.com/series/sumire-16-sai/chapter-18-demon-teacher/"
    },
    {
      "id": "mangadistrict-sumire-16-sai-ch-19",
      "number": "19",
      "title": "Chapter 19 - Lex's Illicit Love",
      "date": "2026-07-02",
      "pages": [],
      "src": "mangadistrict",
      "chapterUrl": "https://mangadistrict.com/series/sumire-16-sai/chapter-19-lexs-illicit-love/"
    },
    {
      "id": "mangadistrict-sumire-16-sai-ch-20",
      "number": "20",
      "title": "Chapter 20 - The Boy in the Nurse's Office (Part One)",
      "date": "2026-07-02",
      "pages": [],
      "src": "mangadistrict",
      "chapterUrl": "https://mangadistrict.com/series/sumire-16-sai/chapter-20-the-boy-in-the-nurses-office-part-one/"
    },
    {
      "id": "mangadistrict-sumire-16-sai-ch-21",
      "number": "21",
      "title": "Chapter 21 - The Boy in the Nurse's Office (Part Two)",
      "date": "2026-07-02",
      "pages": [],
      "src": "mangadistrict",
      "chapterUrl": "https://mangadistrict.com/series/sumire-16-sai/chapter-21-the-boy-in-the-nurses-office-part-two/"
    },
    {
      "id": "mangadistrict-sumire-16-sai-ch-22",
      "number": "22",
      "title": "Chapter 22 - Typhoon Sumire",
      "date": "2026-07-02",
      "pages": [],
      "src": "mangadistrict",
      "chapterUrl": "https://mangadistrict.com/series/sumire-16-sai/chapter-22-typhoon-sumire/"
    },
    {
      "id": "mangadistrict-sumire-16-sai-ch-23",
      "number": "23",
      "title": "Chapter 23 - Welcome to the Maid Cafe!!",
      "date": "2026-07-02",
      "pages": [],
      "src": "mangadistrict",
      "chapterUrl": "https://mangadistrict.com/series/sumire-16-sai/chapter-23-welcome-to-the-maid-cafe/"
    },
    {
      "id": "mangadistrict-sumire-16-sai-ch-24",
      "number": "24",
      "title": "Chapter 24 - Day Two of Culture Festival. Yotsuya's Scary Ghost Story!",
      "date": "2026-07-02",
      "pages": [],
      "src": "mangadistrict",
      "chapterUrl": "https://mangadistrict.com/series/sumire-16-sai/chapter-24-day-two-of-culture-festival-yotsuyas-scary-ghost-story/"
    },
    {
      "id": "mangadistrict-sumire-16-sai-ch-25",
      "number": "25",
      "title": "Chapter 25 - Really! No way! A Story of Sumire's Memories",
      "date": "2026-07-02",
      "pages": [],
      "src": "mangadistrict",
      "chapterUrl": "https://mangadistrict.com/series/sumire-16-sai/chapter-25-really-no-way-a-story-of-sumires-memories/"
    },
    {
      "id": "mangadistrict-sumire-16-sai-ch-26",
      "number": "26",
      "title": "Chapter 26 - The Transfer Student",
      "date": "2026-07-02",
      "pages": [],
      "src": "mangadistrict",
      "chapterUrl": "https://mangadistrict.com/series/sumire-16-sai/chapter-26-the-transfer-student/"
    },
    {
      "id": "mangadistrict-sumire-16-sai-ch-27",
      "number": "27",
      "title": "Chapter 27 - The Butterfly that doesn't stop by flowers",
      "date": "2026-07-02",
      "pages": [],
      "src": "mangadistrict",
      "chapterUrl": "https://mangadistrict.com/series/sumire-16-sai/chapter-27-the-butterfly-that-doesnt-stop-by-flowers/"
    },
    {
      "id": "mangadistrict-sumire-16-sai-ch-28",
      "number": "28",
      "title": "Chapter 28 - I'm not going to give You Mizuki-chan!",
      "date": "2026-07-02",
      "pages": [],
      "src": "mangadistrict",
      "chapterUrl": "https://mangadistrict.com/series/sumire-16-sai/chapter-28-im-not-going-to-give-you-mizuki-chan/"
    },
    {
      "id": "mangadistrict-sumire-16-sai-ch-29",
      "number": "29",
      "title": "Chapter 29 - Beard Match",
      "date": "2026-07-02",
      "pages": [],
      "src": "mangadistrict",
      "chapterUrl": "https://mangadistrict.com/series/sumire-16-sai/chapter-29-beard-match/"
    },
    {
      "id": "mangadistrict-sumire-16-sai-ch-30",
      "number": "30",
      "title": "Chapter 30 - Nurse Sumire!!",
      "date": "2026-07-02",
      "pages": [],
      "src": "mangadistrict",
      "chapterUrl": "https://mangadistrict.com/series/sumire-16-sai/chapter-30-nurse-sumire/"
    },
    {
      "id": "mangadistrict-sumire-16-sai-ch-31",
      "number": "31",
      "title": "Chapter 31 - The Boy and the Cat",
      "date": "2026-07-02",
      "pages": [],
      "src": "mangadistrict",
      "chapterUrl": "https://mangadistrict.com/series/sumire-16-sai/chapter-31-the-boy-and-the-cat/"
    },
    {
      "id": "mangadistrict-sumire-16-sai-ch-32",
      "number": "32",
      "title": "Chapter 32 - Suspect Sumire!!",
      "date": "2026-07-02",
      "pages": [],
      "src": "mangadistrict",
      "chapterUrl": "https://mangadistrict.com/series/sumire-16-sai/chapter-32-suspect-sumire/"
    },
    {
      "id": "mangadistrict-sumire-16-sai-ch-33",
      "number": "33",
      "title": "Chapter 33 - Being Student Council President Tastes like Honey",
      "date": "2026-07-02",
      "pages": [],
      "src": "mangadistrict",
      "chapterUrl": "https://mangadistrict.com/series/sumire-16-sai/chapter-33-being-student-council-president-tastes-like-honey/"
    },
    {
      "id": "mangadistrict-sumire-16-sai-ch-34",
      "number": "34",
      "title": "Chapter 34 - Capitan of Koshien",
      "date": "2026-07-02",
      "pages": [],
      "src": "mangadistrict",
      "chapterUrl": "https://mangadistrict.com/series/sumire-16-sai/chapter-34-capitan-of-koshien/"
    },
    {
      "id": "mangadistrict-sumire-16-sai-ch-35",
      "number": "35",
      "title": "Chapter 35 - Sumire and an Enjoyable Summer Vacation! (Part 1)",
      "date": "2026-07-02",
      "pages": [],
      "src": "mangadistrict",
      "chapterUrl": "https://mangadistrict.com/series/sumire-16-sai/chapter-35-sumire-and-an-enjoyable-summer-vacation-part-1/"
    },
    {
      "id": "mangadistrict-sumire-16-sai-ch-36",
      "number": "36",
      "title": "Chapter 36 - Sumire and an Enjoyable Summer Vacation! (Part 2)",
      "date": "2026-07-02",
      "pages": [],
      "src": "mangadistrict",
      "chapterUrl": "https://mangadistrict.com/series/sumire-16-sai/chapter-36-sumire-and-an-enjoyable-summer-vacation-part-2/"
    },
    {
      "id": "mangadistrict-sumire-16-sai-ch-37",
      "number": "37",
      "title": "Chapter 37 - Sumire and an Enjoyable Summer Vacation! (Part 2)",
      "date": "2026-07-02",
      "pages": [],
      "src": "mangadistrict",
      "chapterUrl": "https://mangadistrict.com/series/sumire-16-sai/chapter-37-sumire-and-an-enjoyable-summer-vacation-part-2/"
    },
    {
      "id": "mangadistrict-sumire-16-sai-ch-38",
      "number": "38",
      "title": "Chapter 38 - Charge!!",
      "date": "2026-07-02",
      "pages": [],
      "src": "mangadistrict",
      "chapterUrl": "https://mangadistrict.com/series/sumire-16-sai/chapter-38-charge/"
    },
    {
      "id": "mangadistrict-sumire-16-sai-ch-39",
      "number": "39",
      "title": "Chapter 39 - Big Sis",
      "date": "2026-07-02",
      "pages": [],
      "src": "mangadistrict",
      "chapterUrl": "https://mangadistrict.com/series/sumire-16-sai/chapter-39-big-sis/"
    },
    {
      "id": "mangadistrict-sumire-16-sai-ch-40",
      "number": "40",
      "title": "Chapter 40 - Take me Sking too!! (Part 1)",
      "date": "2026-07-02",
      "pages": [],
      "src": "mangadistrict",
      "chapterUrl": "https://mangadistrict.com/series/sumire-16-sai/chapter-40-take-me-sking-too-part-1/"
    },
    {
      "id": "mangadistrict-sumire-16-sai-ch-41",
      "number": "41",
      "title": "Chapter 41 - Take me Sking too!! (Part 2)",
      "date": "2026-07-02",
      "pages": [],
      "src": "mangadistrict",
      "chapterUrl": "https://mangadistrict.com/series/sumire-16-sai/chapter-41-take-me-sking-too-part-2/"
    },
    {
      "id": "mangadistrict-sumire-16-sai-ch-42",
      "number": "42",
      "title": "Chapter 42 - Sumire x Sakura x Yamabuki!",
      "date": "2026-07-02",
      "pages": [],
      "src": "mangadistrict",
      "chapterUrl": "https://mangadistrict.com/series/sumire-16-sai/chapter-42-sumire-x-sakura-x-yamabuki/"
    },
    {
      "id": "mangadistrict-sumire-16-sai-ch-43",
      "number": "43",
      "title": "Chapter 43 - Go! Go! Squad Captain!!",
      "date": "2026-07-02",
      "pages": [],
      "src": "mangadistrict",
      "chapterUrl": "https://mangadistrict.com/series/sumire-16-sai/chapter-43-go-go-squad-captain/"
    },
    {
      "id": "mangadistrict-sumire-16-sai-ch-44",
      "number": "44",
      "title": "Chapter 44 - Go! Go! Association Already in a Pinch!",
      "date": "2026-07-02",
      "pages": [],
      "src": "mangadistrict",
      "chapterUrl": "https://mangadistrict.com/series/sumire-16-sai/chapter-44-go-go-association-already-in-a-pinch/"
    },
    {
      "id": "mangadistrict-sumire-16-sai-ch-45",
      "number": "45",
      "title": "Chapter 45 - Do your best Mizuku-chan!!",
      "date": "2026-07-02",
      "pages": [],
      "src": "mangadistrict",
      "chapterUrl": "https://mangadistrict.com/series/sumire-16-sai/chapter-45-do-your-best-mizuku-chan/"
    },
    {
      "id": "mangadistrict-sumire-16-sai-ch-46",
      "number": "46",
      "title": "Chapter 46 - Flower of the Heart",
      "date": "2026-07-02",
      "pages": [],
      "src": "mangadistrict",
      "chapterUrl": "https://mangadistrict.com/series/sumire-16-sai/chapter-46-flower-of-the-heart/"
    },
    {
      "id": "mangadistrict-sumire-16-sai-ch-47",
      "number": "47",
      "title": "Chapter 47 - Gravity of Friendship",
      "date": "2026-07-02",
      "pages": [],
      "src": "mangadistrict",
      "chapterUrl": "https://mangadistrict.com/series/sumire-16-sai/chapter-47-gravity-of-friendship/"
    },
    {
      "id": "mangadistrict-sumire-16-sai-ch-48",
      "number": "48",
      "title": "Chapter 48 - I'm Him and He's me!",
      "date": "2026-07-02",
      "pages": [],
      "src": "mangadistrict",
      "chapterUrl": "https://mangadistrict.com/series/sumire-16-sai/chapter-48-im-him-and-hes-me/"
    },
    {
      "id": "mangadistrict-sumire-16-sai-ch-49",
      "number": "49",
      "title": "Chapter 49 - The Birth of dark Sumire!!",
      "date": "2026-07-02",
      "pages": [],
      "src": "mangadistrict",
      "chapterUrl": "https://mangadistrict.com/series/sumire-16-sai/chapter-49-the-birth-of-dark-sumire/"
    },
    {
      "id": "mangadistrict-sumire-16-sai-ch-50",
      "number": "50",
      "title": "Chapter 50 - The Last Plan!!",
      "date": "2026-07-02",
      "pages": [],
      "src": "mangadistrict",
      "chapterUrl": "https://mangadistrict.com/series/sumire-16-sai/chapter-50-the-last-plan/"
    },
    {
      "id": "mangadistrict-sumire-16-sai-ch-51",
      "number": "51",
      "title": "Chapter 51 - Thank you Sumire!!",
      "date": "2026-07-02",
      "pages": [],
      "src": "mangadistrict",
      "chapterUrl": "https://mangadistrict.com/series/sumire-16-sai/chapter-51-thank-you-sumire/"
    },
    {
      "id": "mangadistrict-sumire-16-sai-ch-52",
      "number": "52",
      "title": "Chapter 52 - Into a Legend",
      "date": "2026-07-02",
      "pages": [],
      "src": "mangadistrict",
      "chapterUrl": "https://mangadistrict.com/series/sumire-16-sai/chapter-52-into-a-legend/"
    }
  ]
}