{
  "en": [
    {
      "id": "mochiron-isharyouseikyuu-itashimasu-1",
      "number": "1",
      "title": "",
      "date": "2019/08/05",
      "pages": []
    },
    {
      "id": "mochiron-isharyouseikyuu-itashimasu-2",
      "number": "2",
      "title": "",
      "date": "2019/08/05",
      "pages": []
    },
    {
      "id": "mochiron-isharyouseikyuu-itashimasu-3",
      "number": "3",
      "title": "",
      "date": "2019/08/05",
      "pages": []
    },
    {
      "id": "mochiron-isharyouseikyuu-itashimasu-4",
      "number": "4",
      "title": "",
      "date": "2019/08/05",
      "pages": []
    },
    {
      "id": "mochiron-isharyouseikyuu-itashimasu-5",
      "number": "5",
      "title": "",
      "date": "2019/09/29",
      "pages": []
    },
    {
      "id": "mochiron-isharyouseikyuu-itashimasu-6",
      "number": "6",
      "title": "",
      "date": "2019/10/31",
      "pages": []
    },
    {
      "id": "mochiron-isharyouseikyuu-itashimasu-7",
      "number": "7",
      "title": "",
      "date": "2019/12/25",
      "pages": []
    },
    {
      "id": "mochiron-isharyouseikyuu-itashimasu-8",
      "number": "8",
      "title": "",
      "date": "2020/01/01",
      "pages": []
    },
    {
      "id": "mochiron-isharyouseikyuu-itashimasu-9",
      "number": "9",
      "title": "",
      "date": "2020/01/18",
      "pages": []
    },
    {
      "id": "mochiron-isharyouseikyuu-itashimasu-10",
      "number": "10",
      "title": "",
      "date": "2020/02/26",
      "pages": []
    },
    {
      "id": "mochiron-isharyouseikyuu-itashimasu-11",
      "number": "11",
      "title": "",
      "date": "2020/02/26",
      "pages": []
    },
    {
      "id": "mochiron-isharyouseikyuu-itashimasu-12",
      "number": "12",
      "title": "",
      "date": "2020/05/20",
      "pages": []
    },
    {
      "id": "mochiron-isharyouseikyuu-itashimasu-13",
      "number": "13",
      "title": "",
      "date": "2020/05/20",
      "pages": []
    },
    {
      "id": "mochiron-isharyouseikyuu-itashimasu-14",
      "number": "14",
      "title": "",
      "date": "2020/11/20",
      "pages": []
    },
    {
      "id": "mochiron-isharyouseikyuu-itashimasu-15",
      "number": "15",
      "title": "",
      "date": "2020/11/20",
      "pages": []
    },
    {
      "id": "mochiron-isharyouseikyuu-itashimasu-16",
      "number": "16",
      "title": "",
      "date": "2021/01/29",
      "pages": []
    },
    {
      "id": "mochiron-isharyouseikyuu-itashimasu-17",
      "number": "17",
      "title": "",
      "date": "2022/01/13",
      "pages": []
    },
    {
      "id": "mochiron-isharyouseikyuu-itashimasu-18",
      "number": "18",
      "title": "",
      "date": "2022/07/13",
      "pages": []
    },
    {
      "id": "mochiron-isharyouseikyuu-itashimasu-18b",
      "number": "18b",
      "title": "",
      "date": "2022/07/16",
      "pages": []
    },
    {
      "id": "mochiron-isharyouseikyuu-itashimasu-19",
      "number": "19",
      "title": "",
      "date": "2023/01/27",
      "pages": []
    },
    {
      "id": "mochiron-isharyouseikyuu-itashimasu-20",
      "number": "20",
      "title": "",
      "date": "2023/01/27",
      "pages": []
    },
    {
      "id": "mochiron-isharyouseikyuu-itashimasu-20a",
      "number": "20a",
      "title": "",
      "date": "2023/07/13",
      "pages": []
    },
    {
      "id": "mochiron-isharyouseikyuu-itashimasu-20b",
      "number": "20b",
      "title": "",
      "date": "2023/07/13",
      "pages": []
    },
    {
      "id": "mochiron-isharyouseikyuu-itashimasu-21a",
      "number": "21a",
      "title": "",
      "date": "2023/07/14",
      "pages": []
    },
    {
      "id": "mochiron-isharyouseikyuu-itashimasu-21b",
      "number": "21b",
      "title": "",
      "date": "2023/07/14",
      "pages": []
    },
    {
      "id": "mochiron-isharyouseikyuu-itashimasu-22a",
      "number": "22a",
      "title": "",
      "date": "2023/07/15",
      "pages": []
    },
    {
      "id": "mochiron-isharyouseikyuu-itashimasu-22b",
      "number": "22b",
      "title": "",
      "date": "2023/07/16",
      "pages": []
    },
    {
      "id": "mochiron-isharyouseikyuu-itashimasu-23a",
      "number": "23a",
      "title": "",
      "date": "2023/07/17",
      "pages": []
    },
    {
      "id": "mochiron-isharyouseikyuu-itashimasu-23b",
      "number": "23b",
      "title": "",
      "date": "2023/07/18",
      "pages": []
    },
    {
      "id": "mochiron-isharyouseikyuu-itashimasu-24",
      "number": "24",
      "title": "",
      "date": "2023/07/18",
      "pages": []
    },
    {
      "id": "mochiron-isharyouseikyuu-itashimasu-25",
      "number": "25",
      "title": "",
      "date": "2023/07/20",
      "pages": []
    },
    {
      "id": "mochiron-isharyouseikyuu-itashimasu-26",
      "number": "26",
      "title": "",
      "date": "2023/07/21",
      "pages": []
    },
    {
      "id": "mochiron-isharyouseikyuu-itashimasu-27",
      "number": "27",
      "title": "",
      "date": "2023/07/24",
      "pages": []
    },
    {
      "id": "mochiron-isharyouseikyuu-itashimasu-28",
      "number": "28",
      "title": "",
      "date": "2023/07/26",
      "pages": []
    },
    {
      "id": "mochiron-isharyouseikyuu-itashimasu-29",
      "number": "29",
      "title": "",
      "date": "2023/07/28",
      "pages": []
    },
    {
      "id": "mochiron-isharyouseikyuu-itashimasu-30",
      "number": "30",
      "title": "",
      "date": "2023/07/29",
      "pages": []
    },
    {
      "id": "mochiron-isharyouseikyuu-itashimasu-31",
      "number": "31",
      "title": "",
      "date": "2024/05/24",
      "pages": []
    }
  ]
}